MANIFEST.in
README.txt
setup.cfg
setup.py
docs/CREDITS.txt
docs/HISTORY.txt
docs/INSTALL.txt
docs/LICENSE.GPL
docs/LICENSE.txt
src/collective/__init__.py
src/collective.facebook.portlets.egg-info/PKG-INFO
src/collective.facebook.portlets.egg-info/SOURCES.txt
src/collective.facebook.portlets.egg-info/dependency_links.txt
src/collective.facebook.portlets.egg-info/entry_points.txt
src/collective.facebook.portlets.egg-info/namespace_packages.txt
src/collective.facebook.portlets.egg-info/not-zip-safe
src/collective.facebook.portlets.egg-info/requires.txt
src/collective.facebook.portlets.egg-info/top_level.txt
src/collective/facebook/__init__.py
src/collective/facebook/portlets/__init__.py
src/collective/facebook/portlets/config.py
src/collective/facebook/portlets/configure.zcml
src/collective/facebook/portlets/fbactivity.pt
src/collective/facebook/portlets/fbactivity.py
src/collective/facebook/portlets/fbwall.pt
src/collective/facebook/portlets/fbwall.py
src/collective/facebook/portlets/setuphandlers.py
src/collective/facebook/portlets/testing.py
src/collective/facebook/portlets/Extensions/Install.py
src/collective/facebook/portlets/Extensions/__init__.py
src/collective/facebook/portlets/locales/collective.facebook.portlets.pot
src/collective/facebook/portlets/locales/manual.pot
src/collective/facebook/portlets/locales/plone.pot
src/collective/facebook/portlets/locales/es/LC_MESSAGES/collective.facebook.portlets.mo
src/collective/facebook/portlets/locales/es/LC_MESSAGES/collective.facebook.portlets.po
src/collective/facebook/portlets/locales/es/LC_MESSAGES/plone.mo
src/collective/facebook/portlets/locales/es/LC_MESSAGES/plone.po
src/collective/facebook/portlets/profiles/default/collective.facebook.portlets_various.txt
src/collective/facebook/portlets/profiles/default/cssregistry.xml
src/collective/facebook/portlets/profiles/default/import_steps.xml
src/collective/facebook/portlets/profiles/default/metadata.xml
src/collective/facebook/portlets/profiles/default/portlets.xml
src/collective/facebook/portlets/profiles/initial/cssregistry.xml
src/collective/facebook/portlets/profiles/initial/metadata.xml
src/collective/facebook/portlets/profiles/uninstall/metadata.xml
src/collective/facebook/portlets/profiles/uninstall/portlets.xml
src/collective/facebook/portlets/static/style.css
src/collective/facebook/portlets/tests/__init__.py
src/collective/facebook/portlets/tests/test_portlet.py
