Metadata-Version: 1.0
Name: collective.facebook.portlets
Version: 1.0b2
Summary: This package implements some Facebook Social Plugins as portlets for your Plone site.
Home-page: https://github.com/collective/collective.facebook.portlets
Author: Franco Pellegrini
Author-email: frapell@gmail.com
License: GPL
Keywords: plone portlet facebook
Platform: UNKNOWN
Classifier: Development Status :: 4 - Beta
Classifier: Environment :: Web Environment
Classifier: Framework :: Plone
Classifier: Framework :: Plone :: 4.1
Classifier: Framework :: Plone :: 4.2
Classifier: Intended Audience :: System Administrators
Classifier: License :: OSI Approved :: GNU General Public License (GPL)
Classifier: Operating System :: OS Independent
Classifier: Programming Language :: JavaScript
Classifier: Programming Language :: Python
Classifier: Programming Language :: Python :: 2.6
Classifier: Programming Language :: Python :: 2.7
Classifier: Topic :: Software Development :: Libraries :: Python Modules
